{
    "追踪者": [
        {
            "等级": 1,
            "生命力": 8,
            "集中力": 4,
            "耐力": 3,
            "力气": 5,
            "敏捷": 4,
            "智力": 2,
            "信仰": 2,
            "感应": 10,
            "总点数": 38,
            "增加点数": 0,
            "HP": 240,
            "FP": 65,
            "ST": 54
        },
        {
            "等级": 2,
            "生命力": 16,
            "集中力": 6,
            "耐力": 6,
            "力气": 18,
            "敏捷": 15,
            "智力": 4,
            "信仰": 4,
            "感应": 10,
            "总点数": 79,
            "增加点数": 41,
            "HP": 400,
            "FP": 75,
            "ST": 60
        },
        {
            "等级": 3,
            "生命力": 19,
            "集中力": 7,
            "耐力": 7,
            "力气": 20,
            "敏捷": 17,
            "智力": 4,
            "信仰": 4,
            "感应": 10,
            "总点数": 88,
            "增加点数": 9,
            "HP": 460,
            "FP": 80,
            "ST": 62
        },
        {
            "等级": 4,
            "生命力": 22,
            "集中力": 8,
            "耐力": 9,
            "力气": 23,
            "敏捷": 19,
            "智力": 5,
            "信仰": 5,
            "感应": 10,
            "总点数": 101,
            "增加点数": 13,
            "HP": 520,
            "FP": 85,
            "ST": 66
        },
        {
            "等级": 5,
            "生命力": 25,
            "集中力": 9,
            "耐力": 11,
            "力气": 25,
            "敏捷": 21,
            "智力": 6,
            "信仰": 6,
            "感应": 10,
            "总点数": 113,
            "增加点数": 12,
            "HP": 580,
            "FP": 90,
            "ST": 70
        },
        {
            "等级": 6,
            "生命力": 28,
            "集中力": 10,
            "耐力": 13,
            "力气": 28,
            "敏捷": 23,
            "智力": 7,
            "信仰": 7,
            "感应": 10,
            "总点数": 126,
            "增加点数": 13,
            "HP": 640,
            "FP": 95,
            "ST": 74
        },
        {
            "等级": 7,
            "生命力": 31,
            "集中力": 11,
            "耐力": 15,
            "力气": 31,
            "敏捷": 25,
            "智力": 8,
            "信仰": 8,
            "感应": 10,
            "总点数": 139,
            "增加点数": 13,
            "HP": 700,
            "FP": 100,
            "ST": 78
        },
        {
            "等级": 8,
            "生命力": 34,
            "集中力": 12,
            "耐力": 16,
            "力气": 33,
            "敏捷": 27,
            "智力": 8,
            "信仰": 8,
            "感应": 10,
            "总点数": 148,
            "增加点数": 9,
            "HP": 760,
            "FP": 105,
            "ST": 80
        },
        {
            "等级": 9,
            "生命力": 37,
            "集中力": 13,
            "耐力": 18,
            "力气": 36,
            "敏捷": 29,
            "智力": 9,
            "信仰": 9,
            "感应": 10,
            "总点数": 161,
            "增加点数": 13,
            "HP": 820,
            "FP": 110,
            "ST": 84
        },
        {
            "等级": 10,
            "生命力": 40,
            "集中力": 14,
            "耐力": 20,
            "力气": 38,
            "敏捷": 31,
            "智力": 10,
            "信仰": 10,
            "感应": 10,
            "总点数": 173,
            "增加点数": 12,
            "HP": 880,
            "FP": 115,
            "ST": 88
        },
        {
            "等级": 11,
            "生命力": 43,
            "集中力": 15,
            "耐力": 22,
            "力气": 41,
            "敏捷": 33,
            "智力": 11,
            "信仰": 11,
            "感应": 10,
            "总点数": 186,
            "增加点数": 13,
            "HP": 940,
            "FP": 120,
            "ST": 92
        },
        {
            "等级": 12,
            "生命力": 46,
            "集中力": 16,
            "耐力": 24,
            "力气": 44,
            "敏捷": 35,
            "智力": 12,
            "信仰": 12,
            "感应": 10,
            "总点数": 199,
            "增加点数": 13,
            "HP": 1000,
            "FP": 125,
            "ST": 96
        },
        {
            "等级": 13,
            "生命力": 48,
            "集中力": 17,
            "耐力": 25,
            "力气": 46,
            "敏捷": 36,
            "智力": 13,
            "信仰": 13,
            "感应": 10,
            "总点数": 208,
            "增加点数": 9,
            "HP": 1040,
            "FP": 130,
            "ST": 98
        },
        {
            "等级": 14,
            "生命力": 50,
            "集中力": 18,
            "耐力": 26,
            "力气": 48,
            "敏捷": 38,
            "智力": 14,
            "信仰": 14,
            "感应": 10,
            "总点数": 218,
            "增加点数": 10,
            "HP": 1080,
            "FP": 135,
            "ST": 100
        },
        {
            "等级": 15,
            "生命力": 52,
            "集中力": 19,
            "耐力": 27,
            "力气": 50,
            "敏捷": 40,
            "智力": 15,
            "信仰": 15,
            "感应": 10,
            "总点数": 228,
            "增加点数": 10,
            "HP": 1120,
            "FP": 140,
            "ST": 102
        }
    ]
}